odoo/addons/easy_my_coop_rest_api/__init__.py
odoo/addons/easy_my_coop_rest_api/__manifest__.py
odoo/addons/easy_my_coop_rest_api/services/__init__.py
odoo/addons/easy_my_coop_rest_api/services/schemas.py
odoo/addons/easy_my_coop_rest_api/services/services_subscription_request.py
odoo12_addon_easy_my_coop_rest_api-12.0.0.1.0.dist-info/METADATA
odoo12_addon_easy_my_coop_rest_api-12.0.0.1.0.dist-info/WHEEL
odoo12_addon_easy_my_coop_rest_api-12.0.0.1.0.dist-info/top_level.txt
odoo12_addon_easy_my_coop_rest_api-12.0.0.1.0.dist-info/RECORD
