Metadata-Version: 2.1
Name: odoo12-addon-easy-my-coop-rest-api
Version: 12.0.0.1.0
Summary: Subscription request service overwritten
Home-page: 
Author: Coopdevs Treball SCCL
Classifier: Programming Language :: Python
Classifier: Framework :: Odoo
Classifier: Framework :: Odoo :: 12.0
Requires-Python: >=3.5
Requires-Dist: odoo12-addon-base-rest-base-structure
Requires-Dist: odoo12-addon-easy-my-coop
Requires-Dist: odoo12-addon-easy-my-coop-es
Requires-Dist: odoo (<12.1dev,>=12.0a)
